point_topic_mcp/__init__.py
point_topic_mcp/server_http.py
point_topic_mcp/server_local.py
point_topic_mcp/auth/__init__.py
point_topic_mcp/connectors/__init__.py
point_topic_mcp/connectors/snowflake.py
point_topic_mcp/context/__init__.py
point_topic_mcp/context/general_db_instructions.py
point_topic_mcp/context/datasets/__init__.py
point_topic_mcp/context/datasets/bi_reports.py
point_topic_mcp/context/datasets/ontology.py
point_topic_mcp/context/datasets/tariffs.py
point_topic_mcp/context/datasets/upc.py
point_topic_mcp/context/datasets/upc_forecast.py
point_topic_mcp/context/datasets/upc_take_up.py
point_topic_mcp/core/__init__.py
point_topic_mcp/core/context_assembly.py
point_topic_mcp/core/tool_manager.py
point_topic_mcp/core/utils.py
point_topic_mcp/prompts/__init__.py
point_topic_mcp/prompts/upc_prompts.py
point_topic_mcp/tools/__init__.py
point_topic_mcp/tools/chart_tools.py
point_topic_mcp/tools/database_tools.py
point_topic_mcp/tools/github_tools.py
point_topic_mcp/tools/server_info_tools.py
point_topic_mcp-0.1.70.dist-info/METADATA
point_topic_mcp-0.1.70.dist-info/WHEEL
point_topic_mcp-0.1.70.dist-info/entry_points.txt
point_topic_mcp-0.1.70.dist-info/RECORD
