Metadata-Version: 2.4
Name: point-topic-mcp
Version: 0.1.70
Summary: UK broadband data analysis MCP server with Snowflake integration
Project-URL: Homepage, https://github.com/point-topic/point-topic-mcp
Project-URL: Repository, https://github.com/point-topic/point-topic-mcp
Author-email: Peter Donaghey <peter.donaghey@point-topic.com>
License: MIT
Keywords: broadband,data-analysis,mcp,snowflake
Classifier: Development Status :: 3 - Alpha
Classifier: Intended Audience :: Developers
Classifier: License :: OSI Approved :: MIT License
Classifier: Programming Language :: Python :: 3
Classifier: Programming Language :: Python :: 3.12
Requires-Python: >=3.12
Requires-Dist: fastmcp>=2.13.0
Requires-Dist: httpx>=0.28.1
Requires-Dist: mcp[cli]>=1.14.0
Requires-Dist: pygithub>=2.1.1
Requires-Dist: python-dotenv>=1.0.0
Requires-Dist: pyyaml>=6.0.0
Requires-Dist: snowflake-connector-python>=3.17.3
Provides-Extra: snowflake
Requires-Dist: pandas>=1.5.0; extra == 'snowflake'
Requires-Dist: pyarrow>=12.0.0; extra == 'snowflake'
